cdk_docker_image_deployment/__init__.py
cdk_docker_image_deployment/py.typed
cdk_docker_image_deployment/_jsii/__init__.py
cdk_docker_image_deployment/_jsii/cdk-docker-image-deployment@0.0.938.jsii.tgz
cdk_docker_image_deployment-0.0.938.dist-info/LICENSE
cdk_docker_image_deployment-0.0.938.dist-info/METADATA
cdk_docker_image_deployment-0.0.938.dist-info/NOTICE
cdk_docker_image_deployment-0.0.938.dist-info/WHEEL
cdk_docker_image_deployment-0.0.938.dist-info/top_level.txt
cdk_docker_image_deployment-0.0.938.dist-info/RECORD
