Metadata-Version: 2.1
Name: cdk-docker-image-deployment
Version: 0.0.938
Summary: This module allows you to copy docker image assets to a repository you control. This can be necessary if you want to build a Docker image in one CDK app and consume it in a different app or outside the CDK.
Home-page: https://github.com/cdklabs/cdk-docker-image-deployment#readme
Author: Parker Scanlon
License: Apache-2.0
Project-URL: Source, https://github.com/cdklabs/cdk-docker-image-deployment.git
Classifier: Intended Audience :: Developers
Classifier: Operating System :: OS Independent
Classifier: Programming Language :: JavaScript
Classifier: Programming Language :: Python :: 3 :: Only
Classifier: Programming Language :: Python :: 3.9
Classifier: Programming Language :: Python :: 3.10
Classifier: Programming Language :: Python :: 3.11
Classifier: Typing :: Typed
Classifier: Development Status :: 5 - Production/Stable
Classifier: License :: OSI Approved
Requires-Python: ~=3.9
License-File: LICENSE
License-File: NOTICE
Requires-Dist: aws-cdk-lib <3.0.0,>=2.24.0
Requires-Dist: constructs <11.0.0,>=10.0.5
Requires-Dist: jsii <2.0.0,>=1.126.0
Requires-Dist: publication >=0.0.3
Requires-Dist: typeguard ==2.13.3
